bioalgorithms-1.1.0.dist-info/METADATA
bioalgorithms-1.1.0.dist-info/WHEEL
bioalgorithms-1.1.0.dist-info/license_files/LICENSE
bioalgorithms/__init__.py
bioalgorithms/bioalgorithms.cpython-312-x86_64-linux-gnu.so
bioalgorithms-1.1.0.dist-info/RECORD
