Metadata-Version: 2.3
Name: bioalgorithms
Version: 1.1.0
Classifier: Programming Language :: Rust
Classifier: Programming Language :: Python :: Implementation :: CPython
Classifier: Programming Language :: Python :: Implementation :: PyPy
License-File: LICENSE
Summary:  A Python library built in Rust for bioinformatics tasks, offering over 30 functions including dynamic programming and optimized data structures for enhanced performance. 
Home-Page: https://github.com/jero98772/bioalgorithms
Author: jero98772 <jero98772@protonmail.com>
Author-email: jero98772 <jero98772@protonmail.com>
License: GPLv3
Requires-Python: >=3.8
